open_feature/__init__.py
open_feature/open_feature_api.py
open_feature/open_feature_client.py
open_feature/open_feature_evaluation_context.py
open_feature/evaluation_context/__init__.py
open_feature/evaluation_context/evaluation_context.py
open_feature/exception/__init__.py
open_feature/exception/exceptions.py
open_feature/flag_evaluation/__init__.py
open_feature/flag_evaluation/error_code.py
open_feature/flag_evaluation/flag_evaluation_details.py
open_feature/flag_evaluation/flag_type.py
open_feature/flag_evaluation/hooks.py
open_feature/flag_evaluation/reason.py
open_feature/hooks/__init__.py
open_feature/hooks/hook.py
open_feature/hooks/hook_context.py
open_feature/hooks/hook_support.py
open_feature/hooks/hook_type.py
open_feature/provider/__init__.py
open_feature/provider/no_op_provider.py
open_feature/provider/provider.py
python_open_feature_sdk-0.0.1.dist-info/LICENSE
python_open_feature_sdk-0.0.1.dist-info/METADATA
python_open_feature_sdk-0.0.1.dist-info/WHEEL
python_open_feature_sdk-0.0.1.dist-info/top_level.txt
python_open_feature_sdk-0.0.1.dist-info/RECORD
