Metadata-Version: 2.1
Name: python-open-feature-sdk
Version: 0.0.1
Summary: Standardizing Feature Flagging for Everyone
Author-email: Open Feature <opensource@dynatrace.com>
License: Apache License
Project-URL: Homepage, https://github.com/open-feature/python-sdk
Classifier: License :: OSI Approved :: Apache Software License
Classifier: Programming Language :: Python
Classifier: Programming Language :: Python :: 3
Requires-Python: >=3.8
License-File: LICENSE
Provides-Extra: dev
Requires-Dist: black ; extra == 'dev'
Requires-Dist: flake8 ; extra == 'dev'
Requires-Dist: isort ; extra == 'dev'
Requires-Dist: pip-tools ; extra == 'dev'
Requires-Dist: pytest ; extra == 'dev'
Requires-Dist: pre-commit ; extra == 'dev'
